solvacaptcha/README.MD
solvacaptcha/__init__.py
solvacaptcha/requirements.txt
solvacaptcha/thirdparty.json
solvacaptcha-0.10.dist-info/LICENSE.rst
solvacaptcha-0.10.dist-info/METADATA
solvacaptcha-0.10.dist-info/WHEEL
solvacaptcha-0.10.dist-info/top_level.txt
solvacaptcha-0.10.dist-info/RECORD
