Metadata-Version: 2.1
Name: solvacaptcha
Version: 0.10
Summary: automates the process of solving reCAPTCHA challenges on web pages when using Selenium
Home-page: https://github.com/hansalemaos/solvacaptcha
Author: Johannes Fischer
Author-email: aulasparticularesdealemaosp@gmail.com
License: MIT
Keywords: reCAPTCHA
Classifier: Development Status :: 4 - Beta
Classifier: Programming Language :: Python :: 3 :: Only
Classifier: Programming Language :: Python :: 3.10
Classifier: Topic :: Software Development :: Libraries :: Python Modules
Classifier: Topic :: Utilities
License-File: LICENSE.rst
Requires-Dist: a-selenium-iframes-crawler
Requires-Dist: audiotranser
Requires-Dist: ffmpegaudiorecord
Requires-Dist: kthread
Requires-Dist: kthread-sleep
Requires-Dist: touchtouch
